rvprog/rvprog.py
rvprog-1.10.0.dist-info/LICENSE
rvprog-1.10.0.dist-info/METADATA
rvprog-1.10.0.dist-info/WHEEL
rvprog-1.10.0.dist-info/entry_points.txt
rvprog-1.10.0.dist-info/top_level.txt
rvprog-1.10.0.dist-info/RECORD
