Metadata-Version: 2.1
Name: rvprog
Version: 1.10.0
Summary: Programming Tool for WCH RISC-V Microcontrollers using WCH-Link
Author-email: Stefan Wagner <wagiminator@web.de>
Maintainer-email: Stefan Wagner <wagiminator@web.de>
License: MIT License
Project-URL: Homepage, https://wagiminator.github.io/
Project-URL: Repository, https://github.com/wagiminator/MCU-Flash-Tools
Project-URL: Issues, https://github.com/wagiminator/MCU-Flash-Tools/issues
Keywords: WCH,CH552,CH32V003,CH32X035,RISC-V,microcontroller
Classifier: Development Status :: 5 - Production/Stable
Classifier: Programming Language :: Python :: 3
Classifier: License :: OSI Approved :: MIT License
Classifier: Operating System :: OS Independent
Classifier: Intended Audience :: Developers
Classifier: Topic :: Software Development :: Embedded Systems
Requires-Python: >=3.6
License-File: LICENSE
Requires-Dist: pyusb
